CHANGES.txt
CONTRIBUTING.md
LICENSE.txt
MANIFEST.in
README.md
setup.py
irt_parameter_estimation/__init__.py
irt_parameter_estimation/_version.py
irt_parameter_estimation/abc_mle.py
irt_parameter_estimation/baker_mle.py
irt_parameter_estimation/util.py
irt_parameter_estimation/zlc_mle.py
irt_parameter_estimation.egg-info/PKG-INFO
irt_parameter_estimation.egg-info/SOURCES.txt
irt_parameter_estimation.egg-info/dependency_links.txt
irt_parameter_estimation.egg-info/requires.txt
irt_parameter_estimation.egg-info/top_level.txt
test/test_irt_parameter_estimation.py