Metadata-Version: 2.1
Name: irt-parameter-estimation
Version: 0.4.1
Summary: Parameter estimation routines for logistic Item Characteristic Curves (ICC) from Item Response Theory (IRT)
Home-page: http://pypi.python.org/pypi/irt_parameter_estimation/
Author: David N. Mashburn
Author-email: david.n.mashburn@gmail.com
License: LICENSE.txt
Platform: UNKNOWN
